LICENSE
README.md
setup.py
bmaquet_tap_salesforce.egg-info/PKG-INFO
bmaquet_tap_salesforce.egg-info/SOURCES.txt
bmaquet_tap_salesforce.egg-info/dependency_links.txt
bmaquet_tap_salesforce.egg-info/entry_points.txt
bmaquet_tap_salesforce.egg-info/requires.txt
bmaquet_tap_salesforce.egg-info/top_level.txt
tap_salesforce/__init__.py
tap_salesforce/__main__.py
tap_salesforce/sync.py
tap_salesforce/salesforce/__init__.py
tap_salesforce/salesforce/bulk.py
tap_salesforce/salesforce/bulk_V2.py
tap_salesforce/salesforce/credentials.py
tap_salesforce/salesforce/exceptions.py
tap_salesforce/salesforce/rest.py