Metadata-Version: 2.1
Name: bmaquet-tap-salesforce
Version: 0.0.10
Summary: Singer.io tap for extracting data from the Salesforce API
Home-page: UNKNOWN
Author: bmaquet
License: UNKNOWN
Platform: UNKNOWN
Classifier: Programming Language :: Python :: 3 :: Only
License-File: LICENSE
